<Factions>
	<Faction name="neutral" logoRGB="logos/confedPri.png" logoSec="logos/confedSec.png"/>
	<Faction name="confed" logoRGB="logos/confedPri.png" secLogoRGB="logos/confedSec.png" contraband="contraband" sparkred="0" sparkgreen="0" sparkblue="1">
		<stats name="privateer" relation=".2"/>
		<stats name="confed" relation="1"/>
		<stats name="aera" relation="-1"/>
		<stats name="rlaan" relation=".2"/>
		<stats name="rlaan_briin" relation=".3"/>
		<Explosion name="explosion_orange.ani"/>
<!--		<CommAnimation>  
			<MoodAnimation name="explosion_orange.ani" sex="0"/>  
		</CommAnimation>  -->
	</Faction>
	<Faction name="aera" logoRGB="logos/aeraPri.png" secLogoRGB="logos/aeraSec.png" contraband="contraband" sparkred="0" sparkgreen="1" sparkblue="0">
		<stats name="privateer" relation="-.5"/>
		<stats name="confed" relation="-1"/>
		<stats name="aera" relation="1"/>
		<stats name="rlaan" relation="-.8"/>
		<stats name="rlaan_briin" relation="-1"/>
		<Explosion name="explosion_orange.ani"/>
<!--		<CommAnimation>  
			<MoodAnimation name="explosion_aera.ani" sex="0"/>  
		</CommAnimation>  -->
	</Faction>
	<Faction name="rlaan" logoRGB="logos/rlaanPri.png" secLogoRGB="logos/rlaanSec.png" contraband="contraband" sparkred=".5" sparkgreen="0" sparkblue="1">
		<stats name="privateer" relation=".05"/>
		<stats name="confed" relation=".15"/>
		<stats name="aera" relation="-.8"/>
		<stats name="rlaan" relation="1"/>
		<stats name="rlaan_briin" relation=".9"/>
		<Explosion name="explosion_orange.ani"/>
<!--		<CommAnimation>  
			<MoodAnimation name="explosion_rlaan.ani" sex="0"/>  
		</CommAnimation>  -->
	</Faction>
	<Faction name="rlaan_briin" logoRGB="logos/rlaan_briinPri.png" secLogoRGB="logos/rlaan_briinSec.png" contraband="contraband" sparkred="1" sparkgreen="0" sparkblue=".8">
		<stats name="privateer" relation="0.05"/>
		<stats name="confed" relation=".7"/>
		<stats name="aera" relation="-1"/>
		<stats name="rlaan" relation="1"/>
		<Explosion name="explosion_orange.ani"/>
<!--		<CommAnimation>  
			<MoodAnimation name="explosion_orange.ani" sex="0"/>  
		</CommAnimation>  -->
	</Faction>
	<Faction name="privateer" logoRGB="logos/privateerPri.png" secLogoRGB="logos/privateerSec.png" contraband="contraband" sparkred=".4" sparkgreen=".4" sparkblue="1">
		<stats name="privateer" relation="0"/>
		<stats name="confed" relation=".2"/>
		<stats name="aera" relation="-.5"/>
		<stats name="rlaan" relation=".05"/>
		<stats name="rlaan_briin" relation="0.05"/>
		<Explosion name="explosion_orange.ani"/>
<!--		<CommAnimation>  
			<MoodAnimation name="explosion_orange.ani" sex="0"/>  
		</CommAnimation>  -->
	</Faction>
	<Faction name="upgrades" logoRGB="logos/confedPri.png" logoSec="logos/confedSec.png"/>
	<Faction name="planets" logoRGB="logos/confedPri.png" logoSec="logos/confedSec.png"/>
</Factions>
